dt_tools/__init__.py
dt_tools/cli/demos/dt_foundation_demo.py
dt_tools/cli/demos/dt_logging_demo.py
dt_tools/cli/demos/dt_misc_helper_demo.py
dt_tools/cli/demos/dt_os_demo.py
dt_tools/cli/demos/dt_project_helper_demo.py
dt_tools/cli/demos/dt_sysinfo_demo.py
dt_tools/cli/set_api_tokens_cli.py
dt_tools/logger/__init__.py
dt_tools/logger/logging_helper.py
dt_tools/misc/__init__.py
dt_tools/misc/api_helper.py
dt_tools/misc/helpers.py
dt_tools/os/__init__.py
dt_tools/os/os_helper.py
dt_tools/os/project_helper.py
dt_foundation-0.1.21.dist-info/entry_points.txt
dt_foundation-0.1.21.dist-info/licenses/LICENSE
dt_foundation-0.1.21.dist-info/METADATA
dt_foundation-0.1.21.dist-info/WHEEL
dt_foundation-0.1.21.dist-info/RECORD
