Metadata-Version: 2.4
Name: dt-foundation
Version: 0.1.21
Summary: [DAmicoTech] Base modules (logging, os,..) for dt-* packages
License: MIT
License-File: LICENSE
Keywords: python,dt-tools,dt-foundation
Author: Al DAmico
Author-email: JavaWiz1@hotmail.com
Requires-Python: >=3.10,<4.0
Classifier: License :: OSI Approved :: MIT License
Classifier: Programming Language :: Python
Classifier: Programming Language :: Python :: 3
Classifier: Programming Language :: Python :: 3.10
Classifier: Programming Language :: Python :: 3.11
Classifier: Programming Language :: Python :: 3.12
Classifier: Programming Language :: Python :: 3.13
Classifier: Programming Language :: Python :: 3.14
Requires-Dist: loguru
Requires-Dist: psutil
Project-URL: Repository, https://github.com/JavaWiz1/dt-foundation
